[
  {
    "ASIN": "B07GH6XFTQ",
    "title": "sillictor コンプレッション ウェア 上下 セット メンズ 長袖 シャツ ＋ ロング タイツ [加圧通気 + 吸汗速乾] 4029+4010 ブルー-S",
    "stars": "⭐⭐⭐✴︎（3.9）｜840件",
    "discount": "🔻 割引：50% OFF",
    "price": "💴 価格：¥1,450",
    "coupon": "",
    "verified": "🕒 確認済み：06/26 12:00PM",
    "link": "👉 Amazonで見る（アフィリエイトリンク）",
    "url": "https://www.amazon.co.jp/dp/B07GH6XFTQ?tag=pkmsalechanne-22",
    "image": "https://i.imgur.com/P4WsRMv.jpeg"
  },
  {
    "ASIN": "B00DAHVKPE",
    "title": "[ユナイテッドアスレ] 5.6オンス ハイクオリティー Tシャツ 500102 [キッズ] 495 ライトピンク 150",
    "stars": "⭐⭐⭐⭐（4.3）｜3974件",
    "discount": "🔻 割引：26% OFF",
    "price": "💴 価格：¥764",
    "coupon": "",
    "verified": "🕒 確認済み：06/26 12:00PM",
    "link": "👉 Amazonで見る（アフィリエイトリンク）",
    "url": "https://www.amazon.co.jp/dp/B00DAHVKPE?tag=pkmsalechanne-22",
    "image": "https://i.imgur.com/8jD8vCH.jpeg"
  },
  {
    "ASIN": "B09YV6DP53",
    "title": "アイリスオーヤマ 水筒 マグボトル スクリュー 350ml ごくごく飲める飲み口 洗いやすい設計 真空断熱6時間キープ 軽量 225g 氷も入る ステンレス ペールグリーン M-S350",
    "stars": "⭐⭐⭐✴︎（3.8）｜278件",
    "discount": "🔻 割引：33% OFF",
    "price": "💴 価格：¥1,596",
    "coupon": "",
    "verified": "🕒 確認済み：06/26 12:00PM",
    "link": "👉 Amazonで見る（アフィリエイトリンク）",
    "url": "https://www.amazon.co.jp/dp/B09YV6DP53?tag=pkmsalechanne-22",
    "image": "https://i.imgur.com/Cqgoq00.jpeg"
  },
  {
    "ASIN": "B0F3XF356L",
    "title": "さらさ 洗濯洗剤 液体 ほのかでやさしい柑橘系の香り 本体 600g",
    "stars": "⭐⭐⭐⭐（4.4）｜768件",
    "discount": "🔻 割引：47% OFF",
    "price": "💴 価格：¥642",
    "coupon": "",
    "verified": "🕒 確認済み：06/26 12:00PM",
    "link": "👉 Amazonで見る（アフィリエイトリンク）",
    "url": "https://www.amazon.co.jp/dp/B0F3XF356L?tag=pkmsalechanne-22",
    "image": "https://i.imgur.com/BKyeVJP.jpeg"
  },
  {
    "ASIN": "B07Z9BFCTM",
    "title": "[ディッキーズ] 874 ワークパンツ オリジナルフィット USAモデル ダークネイビー(DN) 40x30 [並行輸入品]",
    "stars": "⭐⭐⭐⭐（4.3）｜3243件",
    "discount": "🔻 割引：25% OFF",
    "price": "💴 価格：¥4,439",
    "coupon": "",
    "verified": "🕒 確認済み：06/26 12:00PM",
    "link": "👉 Amazonで見る（アフィリエイトリンク）",
    "url": "https://www.amazon.co.jp/dp/B07Z9BFCTM?tag=pkmsalechanne-22",
    "image": "https://i.imgur.com/FvK6nbn.jpeg"
  },
  {
    "ASIN": "B0D6G6FCXQ",
    "title": "クールリング キッズ ネッククール 冷感リング アイスネックリング 大人 首冷却リング クールネック 首元冷却 熱中症対策 暑さ対策 冷たい ひんやり (ピンク, L【大人】)",
    "stars": "⭐⭐⭐✴︎（3.7）｜106件",
    "discount": "🔻 割引：33% OFF",
    "price": "💴 価格：¥398",
    "coupon": "",
    "verified": "🕒 確認済み：06/26 12:00PM",
    "link": "👉 Amazonで見る（アフィリエイトリンク）",
    "url": "https://www.amazon.co.jp/dp/B0D6G6FCXQ?tag=pkmsalechanne-22",
    "image": "https://i.imgur.com/Y3dVwaa.jpeg"
  },
  {
    "ASIN": "B0D31745RJ",
    "title": "[ニューバランス] スニーカー MR530 U530 現行モデル メンズ レディース CSB(WHITE/BROWN) 28.5 cm D",
    "stars": "⭐⭐⭐⭐✴︎（4.5）｜386件",
    "discount": "🔻 割引：27% OFF",
    "price": "💴 価格：¥9,517",
    "coupon": "",
    "verified": "🕒 確認済み：06/26 12:00PM",
    "link": "👉 Amazonで見る（アフィリエイトリンク）",
    "url": "https://www.amazon.co.jp/dp/B0D31745RJ?tag=pkmsalechanne-22",
    "image": "https://i.imgur.com/uNOUt15.jpeg"
  },
  {
    "ASIN": "B0B1TWR79V",
    "title": "アイリスオーヤマ 速乾シャンブレー掛け布団カバー シングル しっとり柔らか 長く使える摩擦耐久性 生地の縮みや型崩れ防止に 部屋干しでも乾きやすい 速乾 ベタつき・ムレ防止で夏も快眠 ピーチスキン加工 洗濯機で丸洗いOK ズレ防止6ヶ所紐付き アイボリー KKC-TP-S",
    "stars": "⭐⭐⭐✴︎（3.9）｜2410件",
    "discount": "🔻 割引：34% OFF",
    "price": "💴 価格：¥1,010",
    "coupon": "",
    "verified": "🕒 確認済み：06/26 12:00PM",
    "link": "👉 Amazonで見る（アフィリエイトリンク）",
    "url": "https://www.amazon.co.jp/dp/B0B1TWR79V?tag=pkmsalechanne-22",
    "image": "https://i.imgur.com/r52jQU2.jpeg"
  },
  {
    "ASIN": "B019DEMMVS",
    "title": "[スピード] フィットネス水着 メンズスパッツ ビックサイズ SD85S63E ブラック/シルバー XA",
    "stars": "⭐⭐⭐⭐（4.1）｜1114件",
    "discount": "🔻 割引：27% OFF",
    "price": "💴 価格：¥4,996",
    "coupon": "",
    "verified": "🕒 確認済み：06/26 12:00PM",
    "link": "👉 Amazonで見る（アフィリエイトリンク）",
    "url": "https://www.amazon.co.jp/dp/B019DEMMVS?tag=pkmsalechanne-22",
    "image": "https://i.imgur.com/qzklX9I.jpeg"
  },
  {
    "ASIN": "B08SR2T1MC",
    "title": "サーモス(THERMOS) まほうびんのベビーストローマグ FJL-350 イエローホワイト (YWH) 350ml 水筒 子供 ステンレス製魔法びん構造 スペアストローセット付き 扱いやすいワンタッチオープン 水滴飛び散り防止機能搭載 4562344378376",
    "stars": "⭐⭐⭐⭐✴︎（4.5）｜477件",
    "discount": "🔻 割引：27% OFF",
    "price": "💴 価格：¥2,946",
    "coupon": "",
    "verified": "🕒 確認済み：06/26 12:00PM",
    "link": "👉 Amazonで見る（アフィリエイトリンク）",
    "url": "https://www.amazon.co.jp/dp/B08SR2T1MC?tag=pkmsalechanne-22",
    "image": "https://i.imgur.com/5AvTDWt.jpeg"
  },
  {
    "ASIN": "B0CTH6Z9W9",
    "title": "VENUS(ヴィーナス) カミソリ 剃刀 女性用 レディース つるすべ肌へ 替刃 3個 エンブレイス",
    "stars": "⭐⭐⭐⭐（4.2）｜60件",
    "discount": "🔻 割引：27% OFF",
    "price": "💴 価格：¥1,140",
    "coupon": "",
    "verified": "🕒 確認済み：06/26 12:00PM",
    "link": "👉 Amazonで見る（アフィリエイトリンク）",
    "url": "https://www.amazon.co.jp/dp/B0CTH6Z9W9?tag=pkmsalechanne-22",
    "image": "https://i.imgur.com/7NBLzRu.jpeg"
  },
  {
    "ASIN": "B0CDRQRZ8M",
    "title": "Z ZONAMA 圧縮袋 電動ポンプ付き 6枚組 衣類収納 ふとん圧縮 旅行 防湿防塵 防カビ 繰り返し使用出来 家庭用 引越し 80×56cm",
    "stars": "⭐⭐⭐✴︎（3.8）｜7397件",
    "discount": "🔻 割引：48% OFF",
    "price": "💴 価格：¥999",
    "coupon": "",
    "verified": "🕒 確認済み：06/26 12:00PM",
    "link": "👉 Amazonで見る（アフィリエイトリンク）",
    "url": "https://www.amazon.co.jp/dp/B0CDRQRZ8M?tag=pkmsalechanne-22",
    "image": "https://i.imgur.com/J5Q4sBP.jpeg"
  },
  {
    "ASIN": "B0BWQDG9Y8",
    "title": "マカロン マジックキューブ 魔方 2×2 3×3 4×4 5×5 立体パズル Magic Cube Set 競技専用 脳トレ 知育玩具 マカロン式 (2×2×2)",
    "stars": "⭐⭐⭐⭐（4.1）｜161件",
    "discount": "🔻 割引：28% OFF",
    "price": "💴 価格：¥680",
    "coupon": "",
    "verified": "🕒 確認済み：06/26 12:00PM",
    "link": "👉 Amazonで見る（アフィリエイトリンク）",
    "url": "https://www.amazon.co.jp/dp/B0BWQDG9Y8?tag=pkmsalechanne-22",
    "image": "https://i.imgur.com/C1hfYVq.jpeg"
  },
  {
    "ASIN": "B0CSBDLSQD",
    "title": "マジックキューブ 3x3x3 Magic Cube 魔方 競技専用キューブ 回転スムーズ 立体パズル 脳トレ 女の子 男の子 プレゼント 知育玩具 小学生 パズルゲーム (ピンク系+パープル系 2024年モデル！)",
    "stars": "⭐⭐⭐⭐（4.1）｜936件",
    "discount": "🔻 割引：32% OFF",
    "price": "💴 価格：¥999",
    "coupon": "",
    "verified": "🕒 確認済み：06/26 12:00PM",
    "link": "👉 Amazonで見る（アフィリエイトリンク）",
    "url": "https://www.amazon.co.jp/dp/B0CSBDLSQD?tag=pkmsalechanne-22",
    "image": "https://i.imgur.com/5ifwaY5.jpeg"
  },
  {
    "ASIN": "B08TZPZF1K",
    "title": "Skechers Women's Loving Life Memory Foam Black/Purple Fashion Sneaker 8.5 Wide US",
    "stars": "⭐⭐⭐⭐（4.4）｜31349件",
    "discount": "🔻 割引：27% OFF",
    "price": "💴 価格：¥10,013",
    "coupon": "",
    "verified": "🕒 確認済み：06/26 12:00PM",
    "link": "👉 Amazonで見る（アフィリエイトリンク）",
    "url": "https://www.amazon.co.jp/dp/B08TZPZF1K?tag=pkmsalechanne-22",
    "image": "https://i.imgur.com/vUnodaL.jpeg"
  },
  {
    "ASIN": "B0BTL72T9Z",
    "title": "スケーター (skater) 箸 スプーンセット 抗菌 はたらくクルマ 日本製 CCA1AG-A",
    "stars": "⭐⭐⭐⭐✴︎（4.5）｜398件",
    "discount": "🔻 割引：42% OFF",
    "price": "💴 価格：¥429",
    "coupon": "",
    "verified": "🕒 確認済み：06/26 12:00PM",
    "link": "👉 Amazonで見る（アフィリエイトリンク）",
    "url": "https://www.amazon.co.jp/dp/B0BTL72T9Z?tag=pkmsalechanne-22",
    "image": "https://i.imgur.com/S9LOt2H.jpeg"
  }
]